pdata/datagen.py
pdata/dirstructure.py
pdata/distributions.py
pdata/ml.py
pdata/pdutils.py
pdata/theanoutils.py
pdata/visualize.py
pdata-0.1.0.dist-info/LICENSE.txt
pdata-0.1.0.dist-info/METADATA
pdata-0.1.0.dist-info/WHEEL
pdata-0.1.0.dist-info/top_level.txt
pdata-0.1.0.dist-info/RECORD
