Metadata-Version: 2.1
Name: pdata
Version: 0.1.0
Summary: UNKNOWN
Home-page: UNKNOWN
Author: Oleksandr Semeniuta
Author-email: oleksandr.semeniuta@gmail.com
License: BSD license
Platform: UNKNOWN
Requires-Dist: numpy
Requires-Dist: scipy
Requires-Dist: pandas
Requires-Dist: scikit-learn
Requires-Dist: theano
Requires-Dist: matplotlib
